config/__init__.py
config/celery.py
config/urls.py
config/wsgi.py
config/settings/__init__.py
config/settings/base.py
config/settings/ci.py
config/settings/development.py
mpesa_api/__init__.py
mpesa_api/core/__init__.py
mpesa_api/core/admin.py
mpesa_api/core/apps.py
mpesa_api/core/models.py
mpesa_api/core/mpesa.py
mpesa_api/core/signals.py
mpesa_api/core/tasks.py
mpesa_api/core/urls.py
mpesa_api/core/views.py
mpesa_api/core/migrations/0001_initial.py
mpesa_api/core/migrations/0002_b2crequest.py
mpesa_api/core/migrations/0003_auto_20171105_0351.py
mpesa_api/core/migrations/0004_auto_20171105_0354.py
mpesa_api/core/migrations/0005_c2brequests.py
mpesa_api/core/migrations/0006_auto_20171106_2339.py
mpesa_api/core/migrations/0007_remove_c2brequest_transaction_id.py
mpesa_api/core/migrations/0008_c2brequest_transaction_id.py
mpesa_api/core/migrations/0009_onlinecheckout.py
mpesa_api/core/migrations/0010_auto_20171108_2148.py
mpesa_api/core/migrations/0011_auto_20171108_2343.py
mpesa_api/core/migrations/0012_onlinecheckout_transaction_date.py
mpesa_api/core/migrations/0013_auto_20171119_2210.py
mpesa_api/core/migrations/0014_authtoken_type.py
mpesa_api/core/migrations/0015_onlinecheckout_is_paybill.py
mpesa_api/core/migrations/__init__.py
mpesa_api/tests/__init__.py
mpesa_api/tests/tests.py
mpesa_api/util/__init__.py
mpesa_api/util/b2cutils.py
mpesa_api/util/c2butils.py
mpesa_api/util/exceptions.py
mpesa_api/util/http.py
mpesa_api/util/managers.py
mpesa_api/util/mocks.py
mpesa_api/util/mpesautils.py
mpesa_api-0.2.3.dist-info/LICENSE
mpesa_api-0.2.3.dist-info/METADATA
mpesa_api-0.2.3.dist-info/WHEEL
mpesa_api-0.2.3.dist-info/top_level.txt
mpesa_api-0.2.3.dist-info/zip-safe
mpesa_api-0.2.3.dist-info/RECORD
