Metadata-Version: 1.1
Name: mpesa-api
Version: 0.2.3
Summary: Mpesa B2C, C2B, STKPush Django library based on the new Api's https://developer.safaricom.co.ke
Home-page: https://github.com/lemaiyan/mpesa_api
Author: Jijo Lemaiyan
Author-email: george@lemaiyan.xyz
License: MIT License
Download-URL: https://github.com/lemaiyan/mpesa_api/archive/0.2.3.tar.gz
Platform: UNKNOWN
Requires: Django (>=2.1.7)
Requires: djangorestframework (>=3.7.3)
Requires: celery (>=4.1.0)
Requires: requests (>=2.18.4)
Requires: decouple (>=3.3)
Requires: rangefilter (>=0.6.1)
